<property>
  <property-name>onMouseDown</property-name>
  <property-extension>
    <category>JAVASCRIPT</category>
    <editor-class>&javascriptEditor;</editor-class>
  </property-extension>
</property>

<property>
  <property-name>onMouseMove</property-name>
  <property-extension>
    <category>JAVASCRIPT</category>
    <editor-class>&javascriptEditor;</editor-class>
  </property-extension>
</property>

<property>
  <property-name>onMouseOut</property-name>
  <property-extension>
    <category>JAVASCRIPT</category>
    <editor-class>&javascriptEditor;</editor-class>
  </property-extension>
</property>

<property>
  <property-name>onMouseOver</property-name>
  <property-extension>
    <category>JAVASCRIPT</category>
    <editor-class>&javascriptEditor;</editor-class>
  </property-extension>
</property>

<property>
  <property-name>onMouseUp</property-name>
  <property-extension>
    <category>JAVASCRIPT</category>
    <editor-class>&javascriptEditor;</editor-class>
  </property-extension>
</property>
